vstruct2/__init__.py
vstruct2/bases.py
vstruct2/compat.py
vstruct2/types.py
vstruct2-2.0.2.dist-info/DESCRIPTION.rst
vstruct2-2.0.2.dist-info/METADATA
vstruct2-2.0.2.dist-info/RECORD
vstruct2-2.0.2.dist-info/WHEEL
vstruct2-2.0.2.dist-info/metadata.json
vstruct2-2.0.2.dist-info/top_level.txt
